azkees/__init__.py
azkees/az.py
azkees/az_base.py
azkees/config.py
azkees/load_envs.py
azkees/logger_setup.py
azkees/vault_handler.py
azkees-6.1.0.dist-info/METADATA
azkees-6.1.0.dist-info/WHEEL
azkees-6.1.0.dist-info/licenses/LICENSE
azkees-6.1.0.dist-info/RECORD
