Metadata-Version: 2.4
Name: azkees
Version: 6.1.0
Summary: A secure and efficient Azure Key Vault client with advanced logging, concurrent operations, and Docker support
License: GPL-3.0-only
License-File: LICENSE
Keywords: azure,key-vault,secrets,security,logging,docker,concurrent,cache
Author: bek42
Author-email: bharani.nitturi@gmail.com
Requires-Python: >=3.11,<4.0
Classifier: Development Status :: 5 - Production/Stable
Classifier: Intended Audience :: Developers
Classifier: License :: OSI Approved :: GNU General Public License v3 (GPLv3)
Classifier: Operating System :: OS Independent
Classifier: Programming Language :: Python :: 3
Classifier: Programming Language :: Python :: 3.11
Classifier: Programming Language :: Python :: 3.12
Classifier: Programming Language :: Python :: 3.13
Classifier: Programming Language :: Python :: 3.14
Classifier: Topic :: Security :: Cryptography
Classifier: Topic :: Software Development :: Libraries :: Python Modules
Classifier: Topic :: System :: Logging
Requires-Dist: azure-identity (>=1.17.1,<2.0.0)
Requires-Dist: azure-keyvault-secrets (>=4.8.0,<5.0.0)
Requires-Dist: msrest (>=0.7.1,<0.8.0)
Requires-Dist: msrestazure (>=0.6.4.post1,<0.7.0)
Requires-Dist: python-dotenv (>=1.0.1,<2.0.0)
Project-URL: Documentation, https://github.com/bek42/azkees/tree/main/docs
Project-URL: Homepage, https://github.com/bek42/azkees
Project-URL: Repository, https://github.com/bek42/azkees
